phlow_auth/__init__.py
phlow_auth/audit.py
phlow_auth/exceptions.py
phlow_auth/middleware.py
phlow_auth/rate_limiter.py
phlow_auth/supabase_helpers.py
phlow_auth/types.py
phlow_auth/integrations/__init__.py
phlow_auth/integrations/fastapi.py
phlow_auth-0.0.5.dist-info/METADATA
phlow_auth-0.0.5.dist-info/WHEEL
phlow_auth-0.0.5.dist-info/RECORD
